<?xml version="1.0" standalone="yes"?>
<LaunchBox>
  <Playlist>
    <PlaylistId>df749cfc-848f-46cf-a82a-238863266cd5</PlaylistId>
    <Name>Batman</Name>
    <NestedName>Batman</NestedName>
    <SortBy>ReleaseDate</SortBy>
    <Notes>[SAGA PARCIAL]
[REVISADO 20/06/2024]
JUEGOS FALTANTES: 13
THE ADVENTURES OF BATMAN &amp; ROBIN ACTIVITY CENTER - PC (1996)
BATMAN: PARTNERS IN PERIL - PC (1996)
BATMAN &amp; ROBIN - GAME.COM (1997)
THE BATMAN: GOTHAM CITY RESCUE - V.SMILE (2003)
BATMAN: JUSTICE UNBALANCED - PC (2003)
THE BATMAN JAKKS PACIFIC - JAKKS PACIFIC TV GAME (2004)
BATMAN 1986 REMAKE - PC (2010)
LEGO BATMAN 2: DC SUPER HEROES - 360,PS3,PS VITA, WII U (2012)
BATMAN - ARCADE (2013)
LEGO BATMAN 3: BEYOND GOTHAM - 360,PS3,PS VITA, WII U (2014)
BATMAN: SAVAGE DAWN - PC (2020)
GOTHAM KNIGHTS -PS5,SERIESX/S,PC (2022)
BATMAN ARKHAM TRILOGY - SWITCH (2023)

ULTIMO:
Batman: The Enemy Within - PS4 (2019)


Batman es una saga de videojuegos de aventura de acción cuyo propietario actual es Warner Bros. y que actualmente cuenta con un total de 39 juegos para Switch, PS4, Xbox One, Wii U, Android, Nintendo 3DS, PSVITA, iPhone, NDS, PSP, Wii, PS3, Xbox 360, PC, Xbox, GameCube, PS2, Game Boy Advance y PS One.

Los juegos de Batman se inspiran en el personaje de DC Comics creado por Bob Kane y Bill Finger. El primero de los títulos, denominado con el nombre del superhéroes a secas, fue una aventura de acción isométrica desarrollada en 1986 por Jon Ritman para ZX Spectrum y otros ordenadores de la época.

Ha habido numerosos títulos tanto originales como inspirados por películas, series de animación y cómics concretos, tanto para consolas como para ordenadores, y de géneros variopintos, como beat'em up, shooters en tercera persona, aventuras narrativas y aventuras de plataformas. El Caballero Oscuro también ha aparecido en otros videojuegos como Injustice: Gods Among Us. La serie iniciada con Batman: Arkham Asylum desarrollada por Rocksteady en 2009 supuso una revolución para los juegos de superhéroes.</Notes>
    <VideoPath />
    <ImageType />
    <Category />
    <BigBoxView />
    <BigBoxTheme />
    <IncludeWithPlatforms>false</IncludeWithPlatforms>
    <AutoPopulate>false</AutoPopulate>
    <SortTitle />
    <IsAutogenerated>false</IsAutogenerated>
    <LocalDbParsed>false</LocalDbParsed>
    <Developer />
    <Manufacturer />
    <Cpu />
    <Memory />
    <Graphics />
    <Sound />
    <Display />
    <Media />
    <MaxControllers />
    <Folder />
    <VideosFolder />
    <FrontImagesFolder />
    <BackImagesFolder />
    <ClearLogoImagesFolder />
    <FanartImagesFolder />
    <ScreenshotImagesFolder />
    <BannerImagesFolder />
    <SteamBannerImagesFolder />
    <ManualsFolder />
    <MusicFolder />
    <ScrapeAs />
    <LastSelectedChild />
    <AndroidThemeVideoPath />
    <HideInBigBox>false</HideInBigBox>
  </Playlist>
  <PlaylistGame>
    <GameId>0911da5b-199c-4a7d-81e4-bd594af2ca29</GameId>
    <LaunchBoxDbId>95524</LaunchBoxDbId>
    <GameTitle>Batman</GameTitle>
    <GameFileName>Batman - Rescue The Rovin (1987) (Pack In Video).zip</GameFileName>
    <GamePlatform>Microsoft MSX</GamePlatform>
    <ManualOrder>0</ManualOrder>
  </PlaylistGame>
  <PlaylistGame>
    <GameId>0374e369-a5cc-41b8-ab0a-20bbd7608e5c</GameId>
    <LaunchBoxDbId>125269</LaunchBoxDbId>
    <GameTitle>Batman: The Caped Crusader</GameTitle>
    <GameFileName>Batman - The Caped Crusader (1988)(Ocean Software).zip</GameFileName>
    <GamePlatform>Amstrad CPC</GamePlatform>
    <ManualOrder>1</ManualOrder>
  </PlaylistGame>
  <PlaylistGame>
    <GameId>77d66506-cdc5-4ff4-9f55-bc303196d3ca</GameId>
    <LaunchBoxDbId>35294</LaunchBoxDbId>
    <GameTitle>Batman: The Caped Crusader</GameTitle>
    <GameFileName>BatmanCapedCrusader.info</GameFileName>
    <GamePlatform>Commodore Amiga</GamePlatform>
    <ManualOrder>2</ManualOrder>
  </PlaylistGame>
  <PlaylistGame>
    <GameId>22114398-5c5d-4d66-90e1-cf284d53e251</GameId>
    <LaunchBoxDbId>125271</LaunchBoxDbId>
    <GameTitle>Batman: The Caped Crusader</GameTitle>
    <GameFileName>Batman - The Caped Crusader (1988)(Ocean)[cr Bladerunners].zip</GameFileName>
    <GamePlatform>Atari ST</GamePlatform>
    <ManualOrder>3</ManualOrder>
  </PlaylistGame>
  <PlaylistGame>
    <GameId>750111e8-dd80-4366-b1a3-9276c1c78159</GameId>
    <LaunchBoxDbId>28287</LaunchBoxDbId>
    <GameTitle>Batman: The Movie</GameTitle>
    <GameFileName>Batman (1986)(Ocean Software)[cr Frankie].zip</GameFileName>
    <GamePlatform>Amstrad CPC</GamePlatform>
    <ManualOrder>4</ManualOrder>
  </PlaylistGame>
  <PlaylistGame>
    <GameId>43f4050f-a4e1-4478-b9ff-665394c0c63f</GameId>
    <LaunchBoxDbId>122469</LaunchBoxDbId>
    <GameTitle>Batman: The Movie</GameTitle>
    <GameFileName>Batman - The Movie (1989)(Ocean)[a].zip</GameFileName>
    <GamePlatform>Atari ST</GamePlatform>
    <ManualOrder>5</ManualOrder>
  </PlaylistGame>
  <PlaylistGame>
    <GameId>90974ba7-37b1-48a0-b0d8-577577e2f346</GameId>
    <LaunchBoxDbId>337</LaunchBoxDbId>
    <GameTitle>Batman</GameTitle>
    <GameFileName>Batman (U) [!].nes</GameFileName>
    <GamePlatform>Nintendo Entertainment System</GamePlatform>
    <ManualOrder>6</ManualOrder>
  </PlaylistGame>
  <PlaylistGame>
    <GameId>e8465c02-9a79-4301-9e04-58c12bedc6de</GameId>
    <LaunchBoxDbId>125268</LaunchBoxDbId>
    <GameTitle>Batman: The Movie</GameTitle>
    <GameFileName>batman.exe</GameFileName>
    <GamePlatform>MS-DOS</GamePlatform>
    <ManualOrder>7</ManualOrder>
  </PlaylistGame>
  <PlaylistGame>
    <GameId>5798feb9-c83d-4c1f-9350-cfdd745dbaa1</GameId>
    <LaunchBoxDbId>10686</LaunchBoxDbId>
    <GameTitle>Batman</GameTitle>
    <GameFileName>batman.zip</GameFileName>
    <GamePlatform>Arcade</GamePlatform>
    <ManualOrder>8</ManualOrder>
  </PlaylistGame>
  <PlaylistGame>
    <GameId>68d12fab-b2cc-43c3-a2c8-3b52a5e121e9</GameId>
    <LaunchBoxDbId>11199</LaunchBoxDbId>
    <GameTitle>Batman: The Video Game</GameTitle>
    <GameFileName>Batman (JU) [!].gb</GameFileName>
    <GamePlatform>Nintendo Game Boy</GamePlatform>
    <ManualOrder>9</ManualOrder>
  </PlaylistGame>
  <PlaylistGame>
    <GameId>ac23f722-d38c-46df-85f4-0130b4a0ce42</GameId>
    <LaunchBoxDbId>4279</LaunchBoxDbId>
    <GameTitle>Batman: The Video Game</GameTitle>
    <GameFileName>Batman - The Video Game (USA).rar</GameFileName>
    <GamePlatform>Sega Genesis</GamePlatform>
    <ManualOrder>10</ManualOrder>
  </PlaylistGame>
  <PlaylistGame>
    <GameId>d234c3bd-ca45-46cb-93ac-32259c82e10e</GameId>
    <LaunchBoxDbId>20243</LaunchBoxDbId>
    <GameTitle>Batman</GameTitle>
    <GameFileName>Batman (Japan).zip</GameFileName>
    <GamePlatform>NEC TurboGrafx-16</GamePlatform>
    <ManualOrder>11</ManualOrder>
  </PlaylistGame>
  <PlaylistGame>
    <GameId>633e4420-efbd-4f8b-aa30-91e70efb744d</GameId>
    <LaunchBoxDbId>18298</LaunchBoxDbId>
    <GameTitle>Batman: Return of the Joker</GameTitle>
    <GameFileName>Batman - Return of the Joker (U) [!].gb</GameFileName>
    <GamePlatform>Nintendo Game Boy</GamePlatform>
    <ManualOrder>12</ManualOrder>
  </PlaylistGame>
  <PlaylistGame>
    <GameId>8e16bf5d-3eba-457e-8d60-3c3d11a54744</GameId>
    <LaunchBoxDbId>3480</LaunchBoxDbId>
    <GameTitle>Batman: Revenge of the Joker</GameTitle>
    <GameFileName>Batman - Revenge of the Joker (U).rar</GameFileName>
    <GamePlatform>Super Nintendo Entertainment System</GamePlatform>
    <ManualOrder>13</ManualOrder>
  </PlaylistGame>
  <PlaylistGame>
    <GameId>4fec061e-22af-4953-b195-6a8cb2f7cfdc</GameId>
    <LaunchBoxDbId>1034</LaunchBoxDbId>
    <GameTitle>Batman: Return of the Joker</GameTitle>
    <GameFileName>Batman - Return of the Joker (U) [!].nes</GameFileName>
    <GamePlatform>Nintendo Entertainment System</GamePlatform>
    <ManualOrder>14</ManualOrder>
  </PlaylistGame>
  <PlaylistGame>
    <GameId>be968b67-a752-40a1-aba9-a29854f754a5</GameId>
    <LaunchBoxDbId>4280</LaunchBoxDbId>
    <GameTitle>Batman: Revenge of the Joker</GameTitle>
    <GameFileName>Batman - Revenge of the Joker (USA).rar</GameFileName>
    <GamePlatform>Sega Genesis</GamePlatform>
    <ManualOrder>15</ManualOrder>
  </PlaylistGame>
  <PlaylistGame>
    <GameId>9047ac77-45fe-408d-8642-d267b7ea08d4</GameId>
    <LaunchBoxDbId>22404</LaunchBoxDbId>
    <GameTitle>Batman Returns</GameTitle>
    <GameFileName>Batman Returns.lnx</GameFileName>
    <GamePlatform>Atari Lynx</GamePlatform>
    <ManualOrder>16</ManualOrder>
  </PlaylistGame>
  <PlaylistGame>
    <GameId>0513dc09-8e91-4549-a81c-06d9902bbb21</GameId>
    <LaunchBoxDbId>5735</LaunchBoxDbId>
    <GameTitle>Batman Returns</GameTitle>
    <GameFileName>Batman Returns (U) [!].rar</GameFileName>
    <GamePlatform>Sega Game Gear</GamePlatform>
    <ManualOrder>17</ManualOrder>
  </PlaylistGame>
  <PlaylistGame>
    <GameId>86676c5d-ccbb-42a8-bd11-2496f8686253</GameId>
    <LaunchBoxDbId>4281</LaunchBoxDbId>
    <GameTitle>Batman Returns</GameTitle>
    <GameFileName>Batman Returns (World).rar</GameFileName>
    <GamePlatform>Sega Genesis</GamePlatform>
    <ManualOrder>18</ManualOrder>
  </PlaylistGame>
  <PlaylistGame>
    <GameId>f3f9cbb7-cbfe-4ad6-b76f-4b61da1c5e35</GameId>
    <LaunchBoxDbId>132443</LaunchBoxDbId>
    <GameTitle>Batman Returns</GameTitle>
    <GameFileName>batman.exe</GameFileName>
    <GamePlatform>MS-DOS</GamePlatform>
    <ManualOrder>19</ManualOrder>
  </PlaylistGame>
  <PlaylistGame>
    <GameId>cc294fe8-b619-4fe3-92cb-39e7dd5f1ebc</GameId>
    <LaunchBoxDbId>35295</LaunchBoxDbId>
    <GameTitle>Batman Returns</GameTitle>
    <GameFileName>BatmanReturns.info</GameFileName>
    <GamePlatform>Commodore Amiga</GamePlatform>
    <ManualOrder>20</ManualOrder>
  </PlaylistGame>
  <PlaylistGame>
    <GameId>34cf0fe9-e2fa-4793-8f28-8be9838e6c58</GameId>
    <LaunchBoxDbId>5245</LaunchBoxDbId>
    <GameTitle>Batman Returns</GameTitle>
    <GameFileName>Batman Returns (UE).rar</GameFileName>
    <GamePlatform>Sega Master System</GamePlatform>
    <ManualOrder>21</ManualOrder>
  </PlaylistGame>
  <PlaylistGame>
    <GameId>e576a647-a4fa-4699-a547-e66a8d39682d</GameId>
    <LaunchBoxDbId>2765</LaunchBoxDbId>
    <GameTitle>Batman Returns</GameTitle>
    <GameFileName>Batman Returns (U) [!].nes</GameFileName>
    <GamePlatform>Nintendo Entertainment System</GamePlatform>
    <ManualOrder>22</ManualOrder>
  </PlaylistGame>
  <PlaylistGame>
    <GameId>0e5c440e-a95e-4d73-a234-f0c06b4e5b91</GameId>
    <LaunchBoxDbId>1517</LaunchBoxDbId>
    <GameTitle>Batman Returns</GameTitle>
    <GameFileName>Batman Returns (U) [!].rar</GameFileName>
    <GamePlatform>Super Nintendo Entertainment System</GamePlatform>
    <ManualOrder>23</ManualOrder>
  </PlaylistGame>
  <PlaylistGame>
    <GameId>342a6735-db8f-4474-b2a9-1bba80a3f87f</GameId>
    <LaunchBoxDbId>11198</LaunchBoxDbId>
    <GameTitle>Batman: The Animated Series</GameTitle>
    <GameFileName>Batman - The Animated Series (U).gb</GameFileName>
    <GamePlatform>Nintendo Game Boy</GamePlatform>
    <ManualOrder>24</ManualOrder>
  </PlaylistGame>
  <PlaylistGame>
    <GameId>10f3a28a-1278-4c80-ae57-970915fb9227</GameId>
    <LaunchBoxDbId>1049</LaunchBoxDbId>
    <GameTitle>The Adventures of Batman &amp; Robin</GameTitle>
    <GameFileName>Adventures of Batman &amp; Robin, The (U).rar</GameFileName>
    <GamePlatform>Super Nintendo Entertainment System</GamePlatform>
    <ManualOrder>25</ManualOrder>
  </PlaylistGame>
  <PlaylistGame>
    <GameId>f352568e-a0aa-4244-b8c7-61aefb74406e</GameId>
    <LaunchBoxDbId>20543</LaunchBoxDbId>
    <GameTitle>The Adventures of Batman &amp; Robin</GameTitle>
    <GameFileName>Adventures of Batman &amp; Robin, The (U) [!].rar</GameFileName>
    <GamePlatform>Sega Game Gear</GamePlatform>
    <ManualOrder>26</ManualOrder>
  </PlaylistGame>
  <PlaylistGame>
    <GameId>463a8442-4de6-4e84-adaf-5c62c55d4569</GameId>
    <LaunchBoxDbId>9415</LaunchBoxDbId>
    <GameTitle>The Adventures of Batman &amp; Robin</GameTitle>
    <GameFileName>Adventures of Batman &amp; Robin, The (USA).rar</GameFileName>
    <GamePlatform>Sega Genesis</GamePlatform>
    <ManualOrder>27</ManualOrder>
  </PlaylistGame>
  <PlaylistGame>
    <GameId>a8f090e6-eeac-414c-b445-c18d65f46855</GameId>
    <LaunchBoxDbId>18297</LaunchBoxDbId>
    <GameTitle>Batman Forever</GameTitle>
    <GameFileName>Batman Forever (U) [!].rar</GameFileName>
    <GamePlatform>Nintendo Game Boy</GamePlatform>
    <ManualOrder>28</ManualOrder>
  </PlaylistGame>
  <PlaylistGame>
    <GameId>7d86607c-db04-4072-8453-69d7eb7617b2</GameId>
    <LaunchBoxDbId>3146</LaunchBoxDbId>
    <GameTitle>Batman Forever</GameTitle>
    <GameFileName>Batman Forever (U) [!].rar</GameFileName>
    <GamePlatform>Super Nintendo Entertainment System</GamePlatform>
    <ManualOrder>29</ManualOrder>
  </PlaylistGame>
  <PlaylistGame>
    <GameId>2f7c2421-dd72-4a14-bb89-8168ef221720</GameId>
    <LaunchBoxDbId>454</LaunchBoxDbId>
    <GameTitle>Batman Forever</GameTitle>
    <GameFileName>Batman Forever (World).rar</GameFileName>
    <GamePlatform>Sega Genesis</GamePlatform>
    <ManualOrder>30</ManualOrder>
  </PlaylistGame>
  <PlaylistGame>
    <GameId>9f953dc7-dde0-46fa-8bc5-b9a93d205e62</GameId>
    <LaunchBoxDbId>21765</LaunchBoxDbId>
    <GameTitle>Batman Forever</GameTitle>
    <GameFileName>Batman Forever (U) [!].rar</GameFileName>
    <GamePlatform>Sega Game Gear</GamePlatform>
    <ManualOrder>31</ManualOrder>
  </PlaylistGame>
  <PlaylistGame>
    <GameId>1dc93371-c226-4959-9152-a76e63886a41</GameId>
    <LaunchBoxDbId>26797</LaunchBoxDbId>
    <GameTitle>Batman Forever</GameTitle>
    <GameFileName>batmanfr.zip</GameFileName>
    <GamePlatform>Arcade</GamePlatform>
    <ManualOrder>32</ManualOrder>
  </PlaylistGame>
  <PlaylistGame>
    <GameId>43cd5128-d980-4c65-9d15-0dc1ff98fbd0</GameId>
    <LaunchBoxDbId>20031</LaunchBoxDbId>
    <GameTitle>Batman Forever: The Arcade Game</GameTitle>
    <GameFileName>Batman Forever - The Arcade Game (USA).7z</GameFileName>
    <GamePlatform>Sony Playstation</GamePlatform>
    <ManualOrder>33</ManualOrder>
  </PlaylistGame>
  <PlaylistGame>
    <GameId>49e6fd6e-f1f4-4c53-b556-3c02d4159379</GameId>
    <LaunchBoxDbId>11570</LaunchBoxDbId>
    <GameTitle>Batman &amp; Robin</GameTitle>
    <GameFileName>Batman &amp; Robin (USA).7z</GameFileName>
    <GamePlatform>Sony Playstation</GamePlatform>
    <ManualOrder>34</ManualOrder>
  </PlaylistGame>
  <PlaylistGame>
    <GameId>2607f6ee-0f92-44c9-8dbb-7f752130b496</GameId>
    <LaunchBoxDbId>1065</LaunchBoxDbId>
    <GameTitle>Batman Beyond: Return of the Joker</GameTitle>
    <GameFileName>Batman Beyond - Return of the Joker (U) [!].z64</GameFileName>
    <GamePlatform>Nintendo 64</GamePlatform>
    <ManualOrder>35</ManualOrder>
  </PlaylistGame>
  <PlaylistGame>
    <GameId>b3cbd733-e408-450a-b495-e9b3fae7e7d8</GameId>
    <LaunchBoxDbId>11571</LaunchBoxDbId>
    <GameTitle>Batman Beyond: Return of the Joker</GameTitle>
    <GameFileName>Batman Beyond - Return of the Joker (USA).7z</GameFileName>
    <GamePlatform>Sony Playstation</GamePlatform>
    <ManualOrder>36</ManualOrder>
  </PlaylistGame>
  <PlaylistGame>
    <GameId>08ba4d9c-b879-4813-85f3-4b2a450ab09f</GameId>
    <LaunchBoxDbId>14551</LaunchBoxDbId>
    <GameTitle>Batman Beyond: Return of the Joker</GameTitle>
    <GameFileName>Batman Beyond - Return of the Joker (U) [C][!].rar</GameFileName>
    <GamePlatform>Nintendo Game Boy Color</GamePlatform>
    <ManualOrder>37</ManualOrder>
  </PlaylistGame>
  <PlaylistGame>
    <GameId>294e3fe2-c374-4317-8927-79c55d180438</GameId>
    <LaunchBoxDbId>22042</LaunchBoxDbId>
    <GameTitle>New Batman Adventures, The: Chaos in Gotham</GameTitle>
    <GameFileName>New Batman Adventures, The - Chaos in Gotham (E) (M6) [C][!].rar</GameFileName>
    <GamePlatform>Nintendo Game Boy Color</GamePlatform>
    <ManualOrder>38</ManualOrder>
  </PlaylistGame>
  <PlaylistGame>
    <GameId>d7a3d804-0b78-4046-b168-90d824e70b48</GameId>
    <LaunchBoxDbId>11569</LaunchBoxDbId>
    <GameTitle>Batman: Gotham City Racer</GameTitle>
    <GameFileName>Batman - Gotham City Racer (USA).7z</GameFileName>
    <GamePlatform>Sony Playstation</GamePlatform>
    <ManualOrder>39</ManualOrder>
  </PlaylistGame>
  <PlaylistGame>
    <GameId>18afd028-6dc1-49a1-abe8-6ef5ae399b12</GameId>
    <LaunchBoxDbId>22238</LaunchBoxDbId>
    <GameTitle>Batman: Vengeance</GameTitle>
    <GameFileName>Batman Vengeance (EU) (Rapid Fire) [0174].rar</GameFileName>
    <GamePlatform>Nintendo Game Boy Advance</GamePlatform>
    <ManualOrder>40</ManualOrder>
  </PlaylistGame>
  <PlaylistGame>
    <GameId>c71f9bf3-4cec-457f-acfa-496d33439012</GameId>
    <LaunchBoxDbId>2569</LaunchBoxDbId>
    <GameTitle>Batman: Vengeance</GameTitle>
    <GameFileName>batman-vengeance.zip</GameFileName>
    <GamePlatform>Nintendo GameCube</GamePlatform>
    <ManualOrder>41</ManualOrder>
  </PlaylistGame>
  <PlaylistGame>
    <GameId>53aabf32-d510-4df1-a849-a30620ea694c</GameId>
    <LaunchBoxDbId>30780</LaunchBoxDbId>
    <GameTitle>Batman: Dark Tomorrow</GameTitle>
    <GameFileName>Batman - Dark tomorrow.iso</GameFileName>
    <GamePlatform>Nintendo GameCube</GamePlatform>
    <ManualOrder>42</ManualOrder>
  </PlaylistGame>
  <PlaylistGame>
    <GameId>33d8f11a-ed32-4d94-b877-199825db35be</GameId>
    <LaunchBoxDbId>3328</LaunchBoxDbId>
    <GameTitle>Batman: Rise of Sin Tzu</GameTitle>
    <GameFileName>Batman - Rise of Sin Tzu (US) (Eurasia) [1223].rar</GameFileName>
    <GamePlatform>Nintendo Game Boy Advance</GamePlatform>
    <ManualOrder>43</ManualOrder>
  </PlaylistGame>
  <PlaylistGame>
    <GameId>d1ecc5ac-fa1c-4935-949d-ebfb295040bd</GameId>
    <LaunchBoxDbId>5834</LaunchBoxDbId>
    <GameTitle>Batman: Rise of Sin Tzu</GameTitle>
    <GameFileName>Batman - Rise Of Sin Tzu.iso</GameFileName>
    <GamePlatform>Nintendo GameCube</GamePlatform>
    <ManualOrder>44</ManualOrder>
  </PlaylistGame>
  <PlaylistGame>
    <GameId>c20cf45d-84b5-477e-a02a-d8472b3f05bd</GameId>
    <LaunchBoxDbId>5833</LaunchBoxDbId>
    <GameTitle>Batman Begins</GameTitle>
    <GameFileName>Batman - Begins.iso</GameFileName>
    <GamePlatform>Nintendo GameCube</GamePlatform>
    <ManualOrder>45</ManualOrder>
  </PlaylistGame>
  <PlaylistGame>
    <GameId>a1820a63-335e-4be7-acb3-88c8f14a156b</GameId>
    <LaunchBoxDbId>18357</LaunchBoxDbId>
    <GameTitle>Batman Begins</GameTitle>
    <GameFileName>Batman Begins (UE) (Trashman) [2021].rar</GameFileName>
    <GamePlatform>Nintendo Game Boy Advance</GamePlatform>
    <ManualOrder>46</ManualOrder>
  </PlaylistGame>
  <PlaylistGame>
    <GameId>ccb30b34-272b-47ba-9a3f-dda12cecd52f</GameId>
    <LaunchBoxDbId>7315</LaunchBoxDbId>
    <GameTitle>Justice League Heroes</GameTitle>
    <GameFileName>Justice League Heroes (USA).iso</GameFileName>
    <GamePlatform>Sony Playstation 2</GamePlatform>
    <ManualOrder>47</ManualOrder>
  </PlaylistGame>
  <PlaylistGame>
    <GameId>72c3bac9-dcc9-4f65-9cdb-480e0ec5520b</GameId>
    <LaunchBoxDbId>26218</LaunchBoxDbId>
    <GameTitle>LEGO Batman: The Videogame</GameTitle>
    <GameFileName>LEGO Batman - The Video Game (Europe) (En,Fr,De,Es,It,Da) (PSP) (PSN).iso</GameFileName>
    <GamePlatform>Sony PSP</GamePlatform>
    <ManualOrder>48</ManualOrder>
  </PlaylistGame>
  <PlaylistGame>
    <GameId>37262316-7a6b-4e5f-8c47-1fb106eafa2e</GameId>
    <LaunchBoxDbId>131496</LaunchBoxDbId>
    <GameTitle>Batman: Arkham Asylum Game of the Year Edition</GameTitle>
    <GameFileName>ShippingPC-BmGame.exe</GameFileName>
    <GamePlatform>Windows</GamePlatform>
    <ManualOrder>49</ManualOrder>
  </PlaylistGame>
  <PlaylistGame>
    <GameId>f49579cf-c77b-4d92-aef4-da7d2db5c5dd</GameId>
    <LaunchBoxDbId>13663</LaunchBoxDbId>
    <GameTitle>Batman: The Brave and the Bold</GameTitle>
    <GameFileName>Batman - The Brave and the Bold - The Videogame (USA) (En,Fr,Es).rvz</GameFileName>
    <GamePlatform>Nintendo Wii</GamePlatform>
    <ManualOrder>50</ManualOrder>
  </PlaylistGame>
  <PlaylistGame>
    <GameId>d7778098-690d-4a6c-bc02-2785a7df10e0</GameId>
    <LaunchBoxDbId>19492</LaunchBoxDbId>
    <GameTitle>Batman: The Brave and the Bold: The Videogame</GameTitle>
    <GameFileName>Batman - The Brave and the Bold - The Videogame (Europe) (En,Fr,De,Es,It,Nl).zip</GameFileName>
    <GamePlatform>Nintendo DS</GamePlatform>
    <ManualOrder>51</ManualOrder>
  </PlaylistGame>
  <PlaylistGame>
    <GameId>5f0bceb5-719b-49e9-84c6-507bba38e520</GameId>
    <LaunchBoxDbId>140650</LaunchBoxDbId>
    <GameTitle>Batman: Arkham City:  Game of the Year Edition</GameTitle>
    <GameFileName>BatmanAC.exe</GameFileName>
    <GamePlatform>Windows</GamePlatform>
    <ManualOrder>52</ManualOrder>
  </PlaylistGame>
  <PlaylistGame>
    <GameId>210cf8a7-6779-46e5-be2d-91b7f73f12fc</GameId>
    <LaunchBoxDbId>17645</LaunchBoxDbId>
    <GameTitle>Batman: Arkham Origins</GameTitle>
    <GameFileName>BatmanOrigins.exe</GameFileName>
    <GamePlatform>Windows</GamePlatform>
    <ManualOrder>53</ManualOrder>
  </PlaylistGame>
  <PlaylistGame>
    <GameId>dffaf5c1-4cbc-4598-aa91-23374222e6fd</GameId>
    <LaunchBoxDbId>18420</LaunchBoxDbId>
    <GameTitle>Injustice: Gods Among Us Ultimate Edition</GameTitle>
    <GameFileName>Injustice.exe</GameFileName>
    <GamePlatform>Sony Playstation 4</GamePlatform>
    <ManualOrder>54</ManualOrder>
  </PlaylistGame>
  <PlaylistGame>
    <GameId>8a235d7f-80d8-4688-95c7-48479111d727</GameId>
    <LaunchBoxDbId>19975</LaunchBoxDbId>
    <GameTitle>Batman: Arkham Origins: Blackgate Deluxe Edition</GameTitle>
    <GameFileName>Game.exe</GameFileName>
    <GamePlatform>Windows</GamePlatform>
    <ManualOrder>55</ManualOrder>
  </PlaylistGame>
  <PlaylistGame>
    <GameId>ccd7be62-9045-4073-877e-51879bc689c6</GameId>
    <LaunchBoxDbId>20814</LaunchBoxDbId>
    <GameTitle>Batman: Arkham Knight</GameTitle>
    <GameFileName>BatmanAK.exe</GameFileName>
    <GamePlatform>Sony Playstation 4</GamePlatform>
    <ManualOrder>56</ManualOrder>
  </PlaylistGame>
  <PlaylistGame>
    <GameId>6f7019d1-bcc0-4d54-af1e-67a188af356c</GameId>
    <LaunchBoxDbId>144823</LaunchBoxDbId>
    <GameTitle>Batman: The Telltale Series</GameTitle>
    <GameFileName>Batman.exe</GameFileName>
    <GamePlatform>Sony Playstation 4</GamePlatform>
    <ManualOrder>57</ManualOrder>
  </PlaylistGame>
  <PlaylistGame>
    <GameId>004a6a60-59ea-492d-9702-19313762dce0</GameId>
    <LaunchBoxDbId>157988</LaunchBoxDbId>
    <GameTitle>Injustice 2: Legendary Edition</GameTitle>
    <GameFileName>Injustice2.exe</GameFileName>
    <GamePlatform>Sony Playstation 4</GamePlatform>
    <ManualOrder>58</ManualOrder>
  </PlaylistGame>
  <PlaylistGame>
    <GameId>9c9c844c-4ad9-49dc-9aee-539e04512596</GameId>
    <LaunchBoxDbId>199734</LaunchBoxDbId>
    <GameTitle>Batman: The Enemy Within</GameTitle>
    <GameFileName>Batman2.exe</GameFileName>
    <GamePlatform>Sony Playstation 4</GamePlatform>
    <ManualOrder>59</ManualOrder>
  </PlaylistGame>
</LaunchBox>