<?xml version="1.0" standalone="yes"?>
<LaunchBox>
  <Playlist>
    <PlaylistId>bea858dc-139f-465e-9d6b-9b21d186d54b</PlaylistId>
    <Name>Fallout</Name>
    <NestedName>Fallout</NestedName>
    <SortBy>ReleaseDate</SortBy>
    <Notes>[SEMI COMPLETA]
[REVISADO 24/06/2024]
JUEGOS FALTANTES: 3
FALLOUT TACTICS: BROTHERHOOD OF STEEL - PC (2001)
FALLOUT: BROTHERHOOD OF STEEL - PS2,XBOX (2004)
FALLOUT: 76 - PS4 (2018)


ULTIMO:
FALLOUT 4: GOTY - PS4 (2015)


Fallout es una saga de videojuegos de rol cuyo propietario actual es Bethesda y que actualmente cuenta con un total de 12 juegos para Switch, PS4, Xbox One, Android, iPhone, PC, PS3, Xbox 360, PS2 y Xbox.

La serie Fallout comenzó en 1997 con los juegos de rol en perspectiva isométrica para PC desarrollados por Black Isle Studios e Interplay Entertainment. Tras un largo periodo de ausencia, Bethesda Game Studios, creadores de The Elder Scrolls, se hicieron con los derechos de esta anacronía posnuclear ambientada en Estados Unidos. En 2008 publicaron Fallout 3, que renovó la serie como un RPG de acción, una fórmula con la que se han publicado varias entregas. También hay juegos derivados o spin-offs de otros géneros, como la gestión de Fallout Shelter y la acción de Fallout: Brotherhood of Steel, e incluso series de televisión.</Notes>
    <VideoPath />
    <ImageType />
    <Category />
    <LastGameId />
    <BigBoxView />
    <BigBoxTheme />
    <IncludeWithPlatforms>false</IncludeWithPlatforms>
    <AutoPopulate>false</AutoPopulate>
    <SortTitle />
    <IsAutogenerated>false</IsAutogenerated>
    <LocalDbParsed>false</LocalDbParsed>
    <Developer />
    <Manufacturer />
    <Cpu />
    <Memory />
    <Graphics />
    <Sound />
    <Display />
    <Media />
    <MaxControllers />
    <Folder />
    <VideosFolder />
    <FrontImagesFolder />
    <BackImagesFolder />
    <ClearLogoImagesFolder />
    <FanartImagesFolder />
    <ScreenshotImagesFolder />
    <BannerImagesFolder />
    <SteamBannerImagesFolder />
    <ManualsFolder />
    <MusicFolder />
    <ScrapeAs />
    <LastSelectedChild />
    <AndroidThemeVideoPath />
    <HideInBigBox>false</HideInBigBox>
  </Playlist>
  <PlaylistGame>
    <GameId>96b1079c-7169-4e81-93a6-80e0c2e78048</GameId>
    <LaunchBoxDbId>122153</LaunchBoxDbId>
    <GameTitle>Fallout</GameTitle>
    <GameFileName>Play Fallout Fixt.lnk</GameFileName>
    <GamePlatform>Windows</GamePlatform>
    <ManualOrder>0</ManualOrder>
  </PlaylistGame>
  <PlaylistGame>
    <GameId>c3054151-15fb-4a4b-8aba-b2814e36f83d</GameId>
    <LaunchBoxDbId>2419</LaunchBoxDbId>
    <GameTitle>Fallout 2: A Post Nuclear Role Playing Game</GameTitle>
    <GameFileName>FALLOUT2.EXE</GameFileName>
    <GamePlatform>Windows</GamePlatform>
    <ManualOrder>1</ManualOrder>
  </PlaylistGame>
  <PlaylistGame>
    <GameId>8cd06ef8-a1dc-4eb6-88ed-d10cbbdd538c</GameId>
    <LaunchBoxDbId>140071</LaunchBoxDbId>
    <GameTitle>Fallout 3: Game of the Year Edition</GameTitle>
    <GameFileName>Fallout3.exe</GameFileName>
    <GamePlatform>Windows</GamePlatform>
    <ManualOrder>2</ManualOrder>
  </PlaylistGame>
  <PlaylistGame>
    <GameId>e520d432-d49c-41d2-9a57-6b3740c635b3</GameId>
    <LaunchBoxDbId>12612</LaunchBoxDbId>
    <GameTitle>Fallout: New Vegas: Ultimate Edition</GameTitle>
    <GameFileName>FalloutNV.exe</GameFileName>
    <GamePlatform>Windows</GamePlatform>
    <ManualOrder>3</ManualOrder>
  </PlaylistGame>
  <PlaylistGame>
    <GameId>a83cd189-2c00-4f52-a195-e2062a13bef0</GameId>
    <LaunchBoxDbId>132195</LaunchBoxDbId>
    <GameTitle>Fallout Shelter</GameTitle>
    <GameFileName>FalloutShelter.exe</GameFileName>
    <GamePlatform>Windows</GamePlatform>
    <ManualOrder>4</ManualOrder>
  </PlaylistGame>
  <PlaylistGame>
    <GameId>c79aae70-697f-45fc-8e7a-6eb5a1fa7db6</GameId>
    <LaunchBoxDbId>162191</LaunchBoxDbId>
    <GameTitle>Fallout 4: Game of the Year Edition</GameTitle>
    <GameFileName>Fallout4.exe</GameFileName>
    <GamePlatform>Sony Playstation 4</GamePlatform>
    <ManualOrder>5</ManualOrder>
  </PlaylistGame>
  <PlaylistGame>
    <GameId>0fccaac1-b123-40a4-aa2e-fe35a382c41b</GameId>
    <LaunchBoxDbId>137932</LaunchBoxDbId>
    <GameTitle>Fallout 4: Game of the Year Edition</GameTitle>
    <GameFileName>Fallout4.exe</GameFileName>
    <GamePlatform>Windows</GamePlatform>
    <ManualOrder>6</ManualOrder>
  </PlaylistGame>
</LaunchBox>