<?xml version="1.0" standalone="yes"?>
<LaunchBox>
  <Playlist>
    <PlaylistId>310caa73-db97-482e-892a-bc80f1eb880b</PlaylistId>
    <Name>Max Payne</Name>
    <NestedName>Max Payne</NestedName>
    <SortBy>ReleaseDate</SortBy>
    <Notes />
    <VideoPath>Videos\Playlists\Max Payne Evolution 2001 - 2022 (360p_30fps_H264-128kbit_AAC).mp4</VideoPath>
    <IncludeWithPlatforms>false</IncludeWithPlatforms>
    <AutoPopulate>false</AutoPopulate>
    <SortTitle />
    <IsAutogenerated>false</IsAutogenerated>
    <LocalDbParsed>false</LocalDbParsed>
    <HideInBigBox>false</HideInBigBox>
  </Playlist>
  <PlaylistGame>
    <GameId>2163c696-5e93-4fac-9383-c9eb142ade1b</GameId>
    <LaunchBoxDbId>780</LaunchBoxDbId>
    <GameTitle>Max Payne</GameTitle>
    <GameFileName />
    <GamePlatform>Windows</GamePlatform>
    <ManualOrder>0</ManualOrder>
  </PlaylistGame>
  <PlaylistGame>
    <GameId>87cbe98b-bccf-4fd3-9c49-0df0f4e4d790</GameId>
    <LaunchBoxDbId>779</LaunchBoxDbId>
    <GameTitle>Max Payne 2: The Fall of Max Payne</GameTitle>
    <GameFileName />
    <GamePlatform>Windows</GamePlatform>
    <ManualOrder>1</ManualOrder>
  </PlaylistGame>
  <PlaylistGame>
    <GameId>aa000d2b-9303-4052-b349-09d1e4901baa</GameId>
    <LaunchBoxDbId>11584</LaunchBoxDbId>
    <GameTitle>Max Payne Advance</GameTitle>
    <GameFileName>Max Payne Advance (EU) (Rising Sun) [1421].rar</GameFileName>
    <GamePlatform>Nintendo Game Boy Advance</GamePlatform>
    <ManualOrder>2</ManualOrder>
  </PlaylistGame>
  <PlaylistGame>
    <GameId>19bef166-7c88-4d60-9629-c6a6bee61064</GameId>
    <LaunchBoxDbId>2089</LaunchBoxDbId>
    <GameTitle>Max Payne 3</GameTitle>
    <GameFileName />
    <GamePlatform>Windows</GamePlatform>
    <ManualOrder>3</ManualOrder>
  </PlaylistGame>
</LaunchBox>