<?xml version="1.0" standalone="yes"?>
<LaunchBox>
  <Playlist>
    <PlaylistId>5b87795a-dec4-42ad-86c7-47c62784ebc1</PlaylistId>
    <Name>Saint Seiya</Name>
    <NestedName>Saint Seiya</NestedName>
    <SortBy>ReleaseDate</SortBy>
    <Notes>[SAGA PARCIAL]
[REVISADO 14/07/2024]
JUEGOS FALTANTES: 5
FAMICOM JUMP: EIYU RETSUDEN - NES (1989)
SAINT SEIYA: TYPING RYU SEI KEN - PC (2003)
JUMP SUPER STARS / ULTIMATE STARS - DS (2005-2006)
SAINT SEIYA ONLINE - PC (2009)
J-STARS VICTORY VS - PS3,PSVITA (2014)


ULTIMO:
JUMP FORCE - PS4 (2019)


Saint Seiya es una saga de videojuegos de lucha cuyo propietario actual es Bandai Namco y que actualmente cuenta con un total de 8 juegos para iPhone, Android, PC, PS4, PSP, PS3 y PS2.

La saga debutó en el año 1987 con un título de rol publicado por Bandai que fue el primero en adaptar al mundo de los videojuegos el popular manga Saint Seiya creado por Masami Kurumada que en España se popularizó gracias al anime de Kozo Morishita y Kazuhito Kikuchi que en nuestro país conocimos por el nombre de Los Caballeros del Zodiaco.

A pesar de que los primeros juegos de la saga eran títulos de rol, la mayoría de las entregas más modernas han apostado por el género de la lucha intentando aprovechar una licencia muy popular que, sin embargo, no ha terminado de cuajar en el mundo de los videojuegos.</Notes>
    <VideoPath />
    <ImageType />
    <Category />
    <BigBoxView />
    <BigBoxTheme />
    <IncludeWithPlatforms>false</IncludeWithPlatforms>
    <AutoPopulate>false</AutoPopulate>
    <SortTitle />
    <IsAutogenerated>false</IsAutogenerated>
    <LocalDbParsed>false</LocalDbParsed>
    <Developer />
    <Manufacturer />
    <Cpu />
    <Memory />
    <Graphics />
    <Sound />
    <Display />
    <Media />
    <MaxControllers />
    <Folder />
    <VideosFolder />
    <FrontImagesFolder />
    <BackImagesFolder />
    <ClearLogoImagesFolder />
    <FanartImagesFolder />
    <ScreenshotImagesFolder />
    <BannerImagesFolder />
    <SteamBannerImagesFolder />
    <ManualsFolder />
    <MusicFolder />
    <ScrapeAs />
    <LastSelectedChild />
    <AndroidThemeVideoPath />
    <HideInBigBox>false</HideInBigBox>
  </Playlist>
  <PlaylistGame>
    <GameId>9811ae54-abb4-410d-8b16-ba3703dc874d</GameId>
    <LaunchBoxDbId>21496</LaunchBoxDbId>
    <GameTitle>Saint Seiya: Ougon Densetsu</GameTitle>
    <GameFileName>Saint Seiya - Ougon Densetsu (J) [T+Eng1.00_KingMike].nes</GameFileName>
    <GamePlatform>Nintendo Entertainment System</GamePlatform>
    <ManualOrder>0</ManualOrder>
  </PlaylistGame>
  <PlaylistGame>
    <GameId>27c7abba-1b3f-4e46-986c-97ce7e9c7a3c</GameId>
    <LaunchBoxDbId>21497</LaunchBoxDbId>
    <GameTitle>Saint Seiya: Ougon Densetsu Kanketsu Hen</GameTitle>
    <GameFileName>Saint Seiya - Ougon Densetsu Kanketsu Hen (J) [!].nes</GameFileName>
    <GamePlatform>Nintendo Entertainment System</GamePlatform>
    <ManualOrder>1</ManualOrder>
  </PlaylistGame>
  <PlaylistGame>
    <GameId>207086b6-9c7b-4a34-a706-8ee735b06cfb</GameId>
    <LaunchBoxDbId>154843</LaunchBoxDbId>
    <GameTitle>Seitoushi Saint Paradise: Saikyou no Senshitachi</GameTitle>
    <GameFileName>SD Saint Seiya Paradise - Saikyou no Senshitachi (J) [T+Spa1.0b_waseiyakusha].gb</GameFileName>
    <GamePlatform>Nintendo Game Boy</GamePlatform>
    <ManualOrder>2</ManualOrder>
  </PlaylistGame>
  <PlaylistGame>
    <GameId>9ced7512-4102-44c1-92e8-c7f929b103c8</GameId>
    <LaunchBoxDbId>27751</LaunchBoxDbId>
    <GameTitle>Saint Seiya: Ougon Densetsuhen Perfect Edition</GameTitle>
    <GameFileName>Saint Seiya - Ougon Densetsu Hen - Perfect Edition (Japan).zip</GameFileName>
    <GamePlatform>WonderSwan Color</GamePlatform>
    <ManualOrder>3</ManualOrder>
  </PlaylistGame>
  <PlaylistGame>
    <GameId>64bf15f8-8d55-4bd0-98ce-3db0c6e68579</GameId>
    <LaunchBoxDbId>31882</LaunchBoxDbId>
    <GameTitle>Saint Seiya: The Sanctuary</GameTitle>
    <GameFileName>Saint Seiya - The Sanctuary (Europe) (En,Fr,De,Es,It).iso</GameFileName>
    <GamePlatform>Sony Playstation 2</GamePlatform>
    <ManualOrder>4</ManualOrder>
  </PlaylistGame>
  <PlaylistGame>
    <GameId>f42fefbb-0bb1-4e02-8864-15be554ff3af</GameId>
    <LaunchBoxDbId>123318</LaunchBoxDbId>
    <GameTitle>Saint Seiya: The Hades</GameTitle>
    <GameFileName>Saint Seiya - The Hades (Europe) (En,Fr,Es,It).iso</GameFileName>
    <GamePlatform>Sony Playstation 2</GamePlatform>
    <ManualOrder>5</ManualOrder>
  </PlaylistGame>
  <PlaylistGame>
    <GameId>6e517bff-73e7-468a-95b3-519709e70572</GameId>
    <LaunchBoxDbId>10688</LaunchBoxDbId>
    <GameTitle>Saint Seiya: Sanctuary Battle</GameTitle>
    <GameFileName>EBOOT.BIN</GameFileName>
    <GamePlatform>Sony Playstation 3</GamePlatform>
    <ManualOrder>6</ManualOrder>
  </PlaylistGame>
  <PlaylistGame>
    <GameId>3c2a94e4-192f-464d-a89a-ede922129d6b</GameId>
    <LaunchBoxDbId>141213</LaunchBoxDbId>
    <GameTitle>Saint Seiya Omega: Ultimate Cosmo</GameTitle>
    <GameFileName>Saint Seiya Omega - Ultimate Cosmo (Japan) (PSN).7z</GameFileName>
    <GamePlatform>Sony PSP</GamePlatform>
    <ManualOrder>7</ManualOrder>
  </PlaylistGame>
  <PlaylistGame>
    <GameId>b9cc7ed6-6ce1-4c13-ba9f-8642258dce04</GameId>
    <LaunchBoxDbId>19071</LaunchBoxDbId>
    <GameTitle>Saint Seiya: Brave Soldiers</GameTitle>
    <GameFileName>EBOOT.BIN</GameFileName>
    <GamePlatform>Sony Playstation 3</GamePlatform>
    <ManualOrder>8</ManualOrder>
  </PlaylistGame>
  <PlaylistGame>
    <GameId>a40cb003-1956-443c-ae6b-3c960ddb3a05</GameId>
    <LaunchBoxDbId>35159</LaunchBoxDbId>
    <GameTitle>Saint Seiya: Soldiers’ Soul</GameTitle>
    <GameFileName>SSSS.exe</GameFileName>
    <GamePlatform>Sony Playstation 4</GamePlatform>
    <ManualOrder>9</ManualOrder>
  </PlaylistGame>
  <PlaylistGame>
    <GameId>d09d5a2a-3b3e-4b53-a32c-66c81a31624f</GameId>
    <LaunchBoxDbId>190240</LaunchBoxDbId>
    <GameTitle>Jump Force</GameTitle>
    <GameFileName>JUMP_FORCE-Win64-Shipping.exe</GameFileName>
    <GamePlatform>Sony Playstation 4</GamePlatform>
    <ManualOrder>10</ManualOrder>
  </PlaylistGame>
</LaunchBox>