<?xml version="1.0" standalone="yes"?>
<LaunchBox>
  <Playlist>
    <PlaylistId>90c0d1a4-5cd2-45d6-87a7-3ec871f1b2e9</PlaylistId>
    <Name>Skate</Name>
    <NestedName>Skate</NestedName>
    <SortBy>ReleaseDate</SortBy>
    <Notes />
    <VideoPath />
    <ImageType />
    <Category />
    <LastGameId />
    <BigBoxView />
    <BigBoxTheme />
    <IncludeWithPlatforms>false</IncludeWithPlatforms>
    <AutoPopulate>false</AutoPopulate>
    <SortTitle />
    <IsAutogenerated>false</IsAutogenerated>
    <LocalDbParsed>false</LocalDbParsed>
    <Developer />
    <Manufacturer />
    <Cpu />
    <Memory />
    <Graphics />
    <Sound />
    <Display />
    <Media />
    <MaxControllers />
    <Folder />
    <VideosFolder />
    <FrontImagesFolder />
    <BackImagesFolder />
    <ClearLogoImagesFolder />
    <FanartImagesFolder />
    <ScreenshotImagesFolder />
    <BannerImagesFolder />
    <SteamBannerImagesFolder />
    <ManualsFolder />
    <MusicFolder />
    <ScrapeAs />
    <LastSelectedChild />
    <AndroidThemeVideoPath />
    <HideInBigBox>false</HideInBigBox>
  </Playlist>
  <PlaylistGame>
    <GameId>0b231de2-9fc2-4c28-a0cc-b7cb31b94ca8</GameId>
    <LaunchBoxDbId>4776</LaunchBoxDbId>
    <GameTitle>The Simpsons Skateboarding</GameTitle>
    <GameFileName>Simpsons, The - Skateboarding (Europe).bin</GameFileName>
    <GamePlatform>Sony Playstation 2</GamePlatform>
    <ManualOrder>0</ManualOrder>
  </PlaylistGame>
  <PlaylistGame>
    <GameId>9d56c9ac-1427-4301-8e60-55bea74df89a</GameId>
    <LaunchBoxDbId>4177</LaunchBoxDbId>
    <GameTitle>Tony Hawk's Pro Skater</GameTitle>
    <GameFileName>Tony Hawk's Pro Skater.cue</GameFileName>
    <GamePlatform>Sony Playstation</GamePlatform>
    <ManualOrder>-1</ManualOrder>
  </PlaylistGame>
  <PlaylistGame>
    <GameId>ef3b05c1-7846-4142-88a7-22317454c16e</GameId>
    <LaunchBoxDbId>406</LaunchBoxDbId>
    <GameTitle>Tony Hawk's Pro Skater</GameTitle>
    <GameFileName>Tony Hawk's Pro Skater (U) [!].v64</GameFileName>
    <GamePlatform>Nintendo 64</GamePlatform>
    <ManualOrder>-1</ManualOrder>
  </PlaylistGame>
  <PlaylistGame>
    <GameId>07204094-38a7-447d-ae81-3c1859a70e53</GameId>
    <LaunchBoxDbId>17695</LaunchBoxDbId>
    <GameTitle>Tony Hawk's Pro Skater</GameTitle>
    <GameFileName>Tony Hawk's Pro Skater (U) [C][!].rar</GameFileName>
    <GamePlatform>Nintendo Game Boy Color</GamePlatform>
    <ManualOrder>-1</ManualOrder>
  </PlaylistGame>
  <PlaylistGame>
    <GameId>a23ad5d7-318b-44f8-ba03-02e696223539</GameId>
    <LaunchBoxDbId>11066</LaunchBoxDbId>
    <GameTitle>Tony Hawk's Pro Skater</GameTitle>
    <GameFileName>Tony Hawk's Pro Skater (USA).7z</GameFileName>
    <GamePlatform>Sega Dreamcast</GamePlatform>
    <ManualOrder>-1</ManualOrder>
  </PlaylistGame>
  <PlaylistGame>
    <GameId>86c5afd1-2065-46d5-88a7-394f14304e9c</GameId>
    <LaunchBoxDbId>9353</LaunchBoxDbId>
    <GameTitle>Tony Hawk's Pro Skater 2</GameTitle>
    <GameFileName>Tony Hawk's Pro Skater 2.cue</GameFileName>
    <GamePlatform>Sony Playstation</GamePlatform>
    <ManualOrder>-1</ManualOrder>
  </PlaylistGame>
  <PlaylistGame>
    <GameId>1975995d-4449-4d9b-91dd-4569edcfc1be</GameId>
    <LaunchBoxDbId>22103</LaunchBoxDbId>
    <GameTitle>Tony Hawk's Pro Skater 2</GameTitle>
    <GameFileName>Tony Hawk's Pro Skater 2 (U) [C][!].rar</GameFileName>
    <GamePlatform>Nintendo Game Boy Color</GamePlatform>
    <ManualOrder>-1</ManualOrder>
  </PlaylistGame>
  <PlaylistGame>
    <GameId>ea327bc1-10f9-42fc-82c9-1941699155ee</GameId>
    <LaunchBoxDbId>11067</LaunchBoxDbId>
    <GameTitle>Tony Hawk's Pro Skater 2</GameTitle>
    <GameFileName>Tony Hawk's Pro Skater 2 (US)].7z</GameFileName>
    <GamePlatform>Sega Dreamcast</GamePlatform>
    <ManualOrder>-1</ManualOrder>
  </PlaylistGame>
  <PlaylistGame>
    <GameId>15707d96-2487-45cd-941a-f95f89f9308c</GameId>
    <LaunchBoxDbId>4119</LaunchBoxDbId>
    <GameTitle>Tony Hawk's Pro Skater 2</GameTitle>
    <GameFileName>Tony Hawk's Pro Skater 2 (UE) (Total Crap) [0033].rar</GameFileName>
    <GamePlatform>Nintendo Game Boy Advance</GamePlatform>
    <ManualOrder>-1</ManualOrder>
  </PlaylistGame>
  <PlaylistGame>
    <GameId>ffac9454-8c75-4f28-b2e2-62c6bcdc1f5b</GameId>
    <LaunchBoxDbId>1218</LaunchBoxDbId>
    <GameTitle>Tony Hawk's Pro Skater 2</GameTitle>
    <GameFileName>Tony Hawk's Pro Skater 2 (U) [!].v64</GameFileName>
    <GamePlatform>Nintendo 64</GamePlatform>
    <ManualOrder>-1</ManualOrder>
  </PlaylistGame>
  <PlaylistGame>
    <GameId>2fc929ed-ceb8-41d0-9e1f-76ca66acd7f8</GameId>
    <LaunchBoxDbId>6265</LaunchBoxDbId>
    <GameTitle>Tony Hawk's Pro Skater 3</GameTitle>
    <GameFileName>Tony Hawk's Pro Skater 3 (USA).iso.rar</GameFileName>
    <GamePlatform>Nintendo GameCube</GamePlatform>
    <ManualOrder>-1</ManualOrder>
  </PlaylistGame>
  <PlaylistGame>
    <GameId>5546fc67-f62b-47f2-a0f9-903d6f5102fc</GameId>
    <LaunchBoxDbId>11667</LaunchBoxDbId>
    <GameTitle>Tony Hawk's Pro Skater 3</GameTitle>
    <GameFileName>Tony Hawk's Pro Skater 3.7z</GameFileName>
    <GamePlatform>Sony Playstation</GamePlatform>
    <ManualOrder>-1</ManualOrder>
  </PlaylistGame>
  <PlaylistGame>
    <GameId>e5e4f826-806a-405a-b355-c2043e5cb7a0</GameId>
    <LaunchBoxDbId>22104</LaunchBoxDbId>
    <GameTitle>Tony Hawk's Pro Skater 3</GameTitle>
    <GameFileName>Tony Hawk's Pro Skater 3 (U) [C][!].rar</GameFileName>
    <GamePlatform>Nintendo Game Boy Color</GamePlatform>
    <ManualOrder>-1</ManualOrder>
  </PlaylistGame>
  <PlaylistGame>
    <GameId>e2aa2b0f-e33b-43a7-9b59-3f858f005cf0</GameId>
    <LaunchBoxDbId>4120</LaunchBoxDbId>
    <GameTitle>Tony Hawk's Pro Skater 3</GameTitle>
    <GameFileName>Tony Hawk's Pro Skater 3 (UE) (The Corporation) [0335].rar</GameFileName>
    <GamePlatform>Nintendo Game Boy Advance</GamePlatform>
    <ManualOrder>-1</ManualOrder>
  </PlaylistGame>
  <PlaylistGame>
    <GameId>1706c9f4-827b-4886-ba0e-2c80081fbcaa</GameId>
    <LaunchBoxDbId>1219</LaunchBoxDbId>
    <GameTitle>Tony Hawk's Pro Skater 3</GameTitle>
    <GameFileName>Tony Hawk's Pro Skater 3 (U).v64</GameFileName>
    <GamePlatform>Nintendo 64</GamePlatform>
    <ManualOrder>-1</ManualOrder>
  </PlaylistGame>
  <PlaylistGame>
    <GameId>9e08de0c-06e9-48b2-a885-9d8f8fd76560</GameId>
    <LaunchBoxDbId>2322</LaunchBoxDbId>
    <GameTitle>Tony Hawk's Pro Skater 4</GameTitle>
    <GameFileName>Tony Hawk's Pro Skater 4 (USA).iso.rar</GameFileName>
    <GamePlatform>Nintendo GameCube</GamePlatform>
    <ManualOrder>-1</ManualOrder>
  </PlaylistGame>
  <PlaylistGame>
    <GameId>5e235158-93cc-40c1-b9ad-c8f22db3fe1e</GameId>
    <LaunchBoxDbId>11668</LaunchBoxDbId>
    <GameTitle>Tony Hawk's Pro Skater 4</GameTitle>
    <GameFileName>Tony Hawk’s Pro Skater 4.cue</GameFileName>
    <GamePlatform>Sony Playstation</GamePlatform>
    <ManualOrder>-1</ManualOrder>
  </PlaylistGame>
  <PlaylistGame>
    <GameId>cf788c54-e53c-4753-abbd-8ae821b606b5</GameId>
    <LaunchBoxDbId>4121</LaunchBoxDbId>
    <GameTitle>Tony Hawk's Pro Skater 4</GameTitle>
    <GameFileName>Tony Hawk's Pro Skater 4 (UE) (Rapid Fire) [0707].rar</GameFileName>
    <GamePlatform>Nintendo Game Boy Advance</GamePlatform>
    <ManualOrder>-1</ManualOrder>
  </PlaylistGame>
  <PlaylistGame>
    <GameId>2bc55b19-5bd1-4795-b3a6-b9d1e86910e8</GameId>
    <LaunchBoxDbId>2323</LaunchBoxDbId>
    <GameTitle>Tony Hawk's Underground</GameTitle>
    <GameFileName>Tony Hawk's Underground (USA).iso.rar</GameFileName>
    <GamePlatform>Nintendo GameCube</GamePlatform>
    <ManualOrder>-1</ManualOrder>
  </PlaylistGame>
  <PlaylistGame>
    <GameId>8ef16633-514d-44ed-85f2-3368d2c36a88</GameId>
    <LaunchBoxDbId>4122</LaunchBoxDbId>
    <GameTitle>Tony Hawk's Underground</GameTitle>
    <GameFileName>Tony Hawk's Underground (UE) (Eurasia) [1226].rar</GameFileName>
    <GamePlatform>Nintendo Game Boy Advance</GamePlatform>
    <ManualOrder>-1</ManualOrder>
  </PlaylistGame>
  <PlaylistGame>
    <GameId>07815155-fa18-4bcb-9d73-362943e09f87</GameId>
    <LaunchBoxDbId>4123</LaunchBoxDbId>
    <GameTitle>Tony Hawk's Underground 2</GameTitle>
    <GameFileName>Tony Hawk's Underground 2 (UE) (Venom) [1693].rar</GameFileName>
    <GamePlatform>Nintendo Game Boy Advance</GamePlatform>
    <ManualOrder>-1</ManualOrder>
  </PlaylistGame>
  <PlaylistGame>
    <GameId>e65fd380-0f47-4707-981f-02c663a2783f</GameId>
    <LaunchBoxDbId>2324</LaunchBoxDbId>
    <GameTitle>Tony Hawk's Underground 2</GameTitle>
    <GameFileName>Tony Hawk's Underground 2 (USA).iso.rar</GameFileName>
    <GamePlatform>Nintendo GameCube</GamePlatform>
    <ManualOrder>-1</ManualOrder>
  </PlaylistGame>
  <PlaylistGame>
    <GameId>4fb4a2ce-ec9a-4ecb-9dab-a12bd5b11478</GameId>
    <LaunchBoxDbId>20096</LaunchBoxDbId>
    <GameTitle>Tony Hawk's Underground 2 Remix</GameTitle>
    <GameFileName>Tony_Hawks_Underground_2_Remix_EUR_PSP-PSPNFO.7z</GameFileName>
    <GamePlatform>Sony PSP</GamePlatform>
    <ManualOrder>-1</ManualOrder>
  </PlaylistGame>
  <PlaylistGame>
    <GameId>be07d4fc-f0e5-4230-813c-2f139a920984</GameId>
    <LaunchBoxDbId>22326</LaunchBoxDbId>
    <GameTitle>Tony Hawk's American Sk8land</GameTitle>
    <GameFileName>Tony Hawk's American Sk8land (EU) (Independent) [2425].rar</GameFileName>
    <GamePlatform>Nintendo Game Boy Advance</GamePlatform>
    <ManualOrder>-1</ManualOrder>
  </PlaylistGame>
  <PlaylistGame>
    <GameId>385b6c98-3ebc-4156-8734-2e9a1df32081</GameId>
    <LaunchBoxDbId>2321</LaunchBoxDbId>
    <GameTitle>Tony Hawk's American Wasteland</GameTitle>
    <GameFileName>Tony Hawk's American Wasteland (USA).iso.rar</GameFileName>
    <GamePlatform>Nintendo GameCube</GamePlatform>
    <ManualOrder>-1</ManualOrder>
  </PlaylistGame>
  <PlaylistGame>
    <GameId>c350dde1-0b15-4f58-b93d-7f3f076d3409</GameId>
    <LaunchBoxDbId>22327</LaunchBoxDbId>
    <GameTitle>Tony Hawk's Downhill Jam</GameTitle>
    <GameFileName>Tony Hawk's Downhill Jam (EU) (Rising Sun) [2578].rar</GameFileName>
    <GamePlatform>Nintendo Game Boy Advance</GamePlatform>
    <ManualOrder>-1</ManualOrder>
  </PlaylistGame>
  <PlaylistGame>
    <GameId>6deae848-3f4a-4840-a38d-9c0757a405a6</GameId>
    <LaunchBoxDbId>19414</LaunchBoxDbId>
    <GameTitle>Tony Hawk's Project 8</GameTitle>
    <GameFileName>Tony Hawk's Project 8 (Europe) (Fr,De,Es,It).7z</GameFileName>
    <GamePlatform>Sony PSP</GamePlatform>
    <ManualOrder>-1</ManualOrder>
  </PlaylistGame>
  <PlaylistGame>
    <GameId>824f9747-9209-4f3c-aa1b-7b2f514ccc57</GameId>
    <LaunchBoxDbId>32130</LaunchBoxDbId>
    <GameTitle>Tony Hawk's Pro Skater 5</GameTitle>
    <GameFileName>default.xex</GameFileName>
    <GamePlatform>Microsoft Xbox 360</GamePlatform>
    <ManualOrder>-1</ManualOrder>
  </PlaylistGame>
  <PlaylistGame>
    <GameId>753e561f-09e4-4d7b-8ad9-b2f3412e0888</GameId>
    <LaunchBoxDbId>187364</LaunchBoxDbId>
    <GameTitle>Skater XL</GameTitle>
    <GameFileName>SkaterXL.exe</GameFileName>
    <GamePlatform>Windows</GamePlatform>
    <ManualOrder>-1</ManualOrder>
  </PlaylistGame>
  <PlaylistGame>
    <GameId>4b1e6862-4456-4d59-958a-f20773c8507f</GameId>
    <LaunchBoxDbId>124396</LaunchBoxDbId>
    <GameTitle>Tony Hawk's Downhill Jam</GameTitle>
    <GameFileName />
    <GamePlatform>Sony Playstation 2</GamePlatform>
    <ManualOrder>-1</ManualOrder>
  </PlaylistGame>
  <PlaylistGame>
    <GameId>a7df9b2c-2e7f-4f00-a24e-be0eb31cf883</GameId>
    <LaunchBoxDbId>14092</LaunchBoxDbId>
    <GameTitle>Tony Hawk's Project 8</GameTitle>
    <GameFileName>Tony Hawk's Project 8 (Europe) (Fr,De,Es,It).iso</GameFileName>
    <GamePlatform>Sony Playstation 2</GamePlatform>
    <ManualOrder>-1</ManualOrder>
  </PlaylistGame>
</LaunchBox>