<?xml version="1.0" standalone="yes"?>
<LaunchBox>
  <Playlist>
    <PlaylistId>f0a1c750-7a30-48e1-9c0e-c7c7b98aa09f</PlaylistId>
    <Name>Tarzan</Name>
    <NestedName>Tarzan</NestedName>
    <SortBy>ReleaseDate</SortBy>
    <Notes>[SAGA PARCIAL]
[REVISADO 30/06/2024]
JUEGOS FALTANTES: 10
TARZAN OF THE APES - ATARI 400,800,XL,XE (1984)
TARZAN - BBC MICRO (1984)
TARZAN - ZX SPECTRUM (1986)
TARZAN - COMMODORE 64 (1986)
LEGEND OF TARZAN - BBC MICRO (1987)
TARZAN GOES APE! - ZX SPECTRUM (1991)
TARZAN GOES APE! - COMMODORE 64 (1991)
DISNEY'S TARZAN ACTIVITY CENTER - PC (1999)
TARZAN UNLEASHED - PC (2013)
TARZAN VR - PC (2020)


ULTIMO:
DISNEY'S TARZAN: RETURN TO THE JUNGLE - GBA (2002)


Mostrando los juegos más recientes sobre tarzan:

N64 Disney's Tarzan   Año: 2000
Plataformas / Plataformas 2D

PS2 Tarzan Freeride   Año: 2001
Aventura de acción

GCN Disney's Tarzan Untamed   Año: 2002
Aventura de acción

PC Tarzan VR   Año: 2020
Aventura de acción / Realidad Virtual / Supervivencia

PS4 Tarzan VR   Año: 2021
Aventura de acción / Realidad Virtual / Supervivencia</Notes>
    <VideoPath />
    <ImageType />
    <Category />
    <LastGameId />
    <BigBoxView />
    <BigBoxTheme />
    <IncludeWithPlatforms>false</IncludeWithPlatforms>
    <AutoPopulate>false</AutoPopulate>
    <SortTitle />
    <IsAutogenerated>false</IsAutogenerated>
    <LocalDbParsed>false</LocalDbParsed>
    <Developer />
    <Manufacturer />
    <Cpu />
    <Memory />
    <Graphics />
    <Sound />
    <Display />
    <Media />
    <MaxControllers />
    <Folder />
    <VideosFolder />
    <FrontImagesFolder />
    <BackImagesFolder />
    <ClearLogoImagesFolder />
    <FanartImagesFolder />
    <ScreenshotImagesFolder />
    <BannerImagesFolder />
    <SteamBannerImagesFolder />
    <ManualsFolder />
    <MusicFolder />
    <ScrapeAs />
    <LastSelectedChild />
    <AndroidThemeVideoPath />
    <HideInBigBox>false</HideInBigBox>
  </Playlist>
  <PlaylistGame>
    <GameId>784898dd-fa2f-440b-a3f3-6788cbfa67d3</GameId>
    <LaunchBoxDbId>160060</LaunchBoxDbId>
    <GameTitle>Tarzan</GameTitle>
    <GameFileName>Tarzan (1986)(Martech Games).zip</GameFileName>
    <GamePlatform>Amstrad CPC</GamePlatform>
    <ManualOrder>0</ManualOrder>
  </PlaylistGame>
  <PlaylistGame>
    <GameId>194fd40b-eb04-4186-837c-48d93ade2aca</GameId>
    <LaunchBoxDbId>21779</LaunchBoxDbId>
    <GameTitle>Tarzan: Lord of the Jungle</GameTitle>
    <GameFileName>Tarzan (U) [!].gb</GameFileName>
    <GamePlatform>Nintendo Game Boy</GamePlatform>
    <ManualOrder>1</ManualOrder>
  </PlaylistGame>
  <PlaylistGame>
    <GameId>4c679b52-324f-4a54-a2b5-08fb98b642e0</GameId>
    <LaunchBoxDbId>25448</LaunchBoxDbId>
    <GameTitle>Disney's Tarzan</GameTitle>
    <GameFileName>Disney's Tarzan (U) [C][!].rar</GameFileName>
    <GamePlatform>Nintendo Game Boy Color</GamePlatform>
    <ManualOrder>2</ManualOrder>
  </PlaylistGame>
  <PlaylistGame>
    <GameId>ba8a7905-5c40-4f22-9331-ef22f88ba459</GameId>
    <LaunchBoxDbId>8284</LaunchBoxDbId>
    <GameTitle>Tarzan</GameTitle>
    <GameFileName>Tarzan.7z</GameFileName>
    <GamePlatform>Sony Playstation</GamePlatform>
    <ManualOrder>3</ManualOrder>
  </PlaylistGame>
  <PlaylistGame>
    <GameId>dbd37ecc-a5f2-44c6-9d88-a7b058893aa1</GameId>
    <LaunchBoxDbId>3148</LaunchBoxDbId>
    <GameTitle>Tarzan</GameTitle>
    <GameFileName>Tarzan (U) [!].z64</GameFileName>
    <GamePlatform>Nintendo 64</GamePlatform>
    <ManualOrder>4</ManualOrder>
  </PlaylistGame>
  <PlaylistGame>
    <GameId>abe81f81-eb4c-44bb-b413-27c225c1751a</GameId>
    <LaunchBoxDbId>30811</LaunchBoxDbId>
    <GameTitle>Tarzan Untamed</GameTitle>
    <GameFileName>Disney's Tarzan - Untamed (USA) (En,Fr).iso.rar</GameFileName>
    <GamePlatform>Nintendo GameCube</GamePlatform>
    <ManualOrder>5</ManualOrder>
  </PlaylistGame>
  <PlaylistGame>
    <GameId>4e26751a-4252-431b-87c2-4fb0f5d5366e</GameId>
    <LaunchBoxDbId>26158</LaunchBoxDbId>
    <GameTitle>Tarzan: Return to the Jungle</GameTitle>
    <GameFileName>Tarzan - Return to the Jungle (UE) (Mode 7) [0683].rar</GameFileName>
    <GamePlatform>Nintendo Game Boy Advance</GamePlatform>
    <ManualOrder>6</ManualOrder>
  </PlaylistGame>
</LaunchBox>