<?xml version="1.0" standalone="yes"?>
<LaunchBox>
  <Playlist>
    <PlaylistId>02710362-2e4c-49d5-bca4-95b19bc52c44</PlaylistId>
    <Name>Tom Clancy's Ghost Recon</Name>
    <NestedName>Tom Clancy's Ghost Recon</NestedName>
    <SortBy>ReleaseDate</SortBy>
    <Notes>[SAGA COMPLETA]
[REVISADO 05/07/2024]
JUEGOS FALTANTES: 4
TOM CLANCY'S GHOST RECON - WII (2010)
TOM CLANCY'S GHOST RECON SHADOW WARS - 3DS (2011)
TOM CLANCY'S GHOST RECON PHANTOMS - PC (2014)
TOM CLANCY'S GHOST RECON BREAKPOINT - PS4 (2020)


ULTMO:
TOM CLANCY'S GHOST RECON WILDLANS - PS4 (2017)



Ghost Recon es una saga de videojuegos de shooter cuyo propietario actual es Ubisoft y que actualmente cuenta con un total de 19 juegos para Xbox Series X/S, Xbox One, PS4, Nintendo 3DS, Wii, PS3, PSP, Xbox 360, GameCube, N-Gage, Xbox, PS2 y PC.

Tom Clancy's Ghost Recon nació como un shooter táctico desarrollado por Red Storm Entertainment para PC, Xbox, PS2 y GameCube en 2001 baja el paraguas de la marca Tom Clancy. La serie tiene una temática militarista y sigue a un grupo de fuerzas especiales del ejército estadounidense en distintos conflictos ficticios del futuro próximo. A lo largo de los años han aparecido entregas que llevan la jugabilidad táctica al mundo abierto y/o al multijugador en línea. Más allá de a los ordenadores y las consolas de sobremesa, la serie se ha llevado a plataformas como las consolas portátiles y las redes sociales.</Notes>
    <VideoPath>Videos\Playlists\Tom Clancy's Ghost Recon.mp4</VideoPath>
    <ImageType />
    <Category />
    <LastGameId />
    <BigBoxView />
    <BigBoxTheme />
    <IncludeWithPlatforms>false</IncludeWithPlatforms>
    <AutoPopulate>false</AutoPopulate>
    <SortTitle />
    <IsAutogenerated>false</IsAutogenerated>
    <LocalDbParsed>false</LocalDbParsed>
    <Developer />
    <Manufacturer />
    <Cpu />
    <Memory />
    <Graphics />
    <Sound />
    <Display />
    <Media />
    <MaxControllers />
    <Folder />
    <VideosFolder />
    <FrontImagesFolder />
    <BackImagesFolder />
    <ClearLogoImagesFolder />
    <FanartImagesFolder />
    <ScreenshotImagesFolder />
    <BannerImagesFolder />
    <SteamBannerImagesFolder />
    <ManualsFolder />
    <MusicFolder />
    <ScrapeAs />
    <LastSelectedChild />
    <AndroidThemeVideoPath />
    <HideInBigBox>false</HideInBigBox>
  </Playlist>
  <PlaylistGame>
    <GameId>31732d7b-7f1a-424c-b155-f4d52fabbdab</GameId>
    <LaunchBoxDbId>8554</LaunchBoxDbId>
    <GameTitle>Tom Clancy's Ghost Recon</GameTitle>
    <GameFileName>GhostRecon.exe</GameFileName>
    <GamePlatform>Windows</GamePlatform>
    <ManualOrder>0</ManualOrder>
  </PlaylistGame>
  <PlaylistGame>
    <GameId>682b1af5-d547-46b6-929c-bdb0a82ba45f</GameId>
    <LaunchBoxDbId>13695</LaunchBoxDbId>
    <GameTitle>Tom Clancy's Ghost Recon: Desert Siege</GameTitle>
    <GameFileName>GhostRecon.exe</GameFileName>
    <GamePlatform>Windows</GamePlatform>
    <ManualOrder>1</ManualOrder>
  </PlaylistGame>
  <PlaylistGame>
    <GameId>186b2c52-2cf0-4ecb-a503-f739138a1e82</GameId>
    <LaunchBoxDbId>13757</LaunchBoxDbId>
    <GameTitle>Tom Clancy's Ghost Recon: Island Thunder</GameTitle>
    <GameFileName>GhostRecon.exe</GameFileName>
    <GamePlatform>Windows</GamePlatform>
    <ManualOrder>2</ManualOrder>
  </PlaylistGame>
  <PlaylistGame>
    <GameId>9e53812a-aa84-446c-acdd-ccdb70b7eeb6</GameId>
    <LaunchBoxDbId>9700</LaunchBoxDbId>
    <GameTitle>Tom Clancy's Ghost Recon: Jungle Storm</GameTitle>
    <GameFileName>Tom Clancy's Ghost Recon - Jungle Storm (Europe) (En,Fr,De,Es,It).iso</GameFileName>
    <GamePlatform>Sony Playstation 2</GamePlatform>
    <ManualOrder>3</ManualOrder>
  </PlaylistGame>
  <PlaylistGame>
    <GameId>248b6f2b-1a1e-4ee4-ba76-0991a1ef4f5d</GameId>
    <LaunchBoxDbId>6982</LaunchBoxDbId>
    <GameTitle>Tom Clancy's Ghost Recon 2</GameTitle>
    <GameFileName>Tom Clancy's Ghost Recon 2 (USA) (En,Fr,Es).iso.rar</GameFileName>
    <GamePlatform>Nintendo GameCube</GamePlatform>
    <ManualOrder>4</ManualOrder>
  </PlaylistGame>
  <PlaylistGame>
    <GameId>1f37ee0d-e815-406f-8fa0-f09b9094f7d4</GameId>
    <LaunchBoxDbId>6184</LaunchBoxDbId>
    <GameTitle>Tom Clancy's Ghost Recon 2: Summit Strike</GameTitle>
    <GameFileName />
    <GamePlatform>Microsoft Xbox</GamePlatform>
    <ManualOrder>5</ManualOrder>
  </PlaylistGame>
  <PlaylistGame>
    <GameId>e1e5549c-e994-456c-b661-e6290520159b</GameId>
    <LaunchBoxDbId>12029</LaunchBoxDbId>
    <GameTitle>Tom Clancy's Ghost Recon: Advanced Warfighter</GameTitle>
    <GameFileName>GRAW.exe</GameFileName>
    <GamePlatform>Windows</GamePlatform>
    <ManualOrder>6</ManualOrder>
  </PlaylistGame>
  <PlaylistGame>
    <GameId>43430181-b5e6-4de2-b795-f00919201b1c</GameId>
    <LaunchBoxDbId>8917</LaunchBoxDbId>
    <GameTitle>Tom Clancy's Ghost Recon: Advanced Warfighter 2</GameTitle>
    <GameFileName>graw2.exe</GameFileName>
    <GamePlatform>Windows</GamePlatform>
    <ManualOrder>7</ManualOrder>
  </PlaylistGame>
  <PlaylistGame>
    <GameId>92097b7e-77f6-4e77-82f9-1209abf8ee96</GameId>
    <LaunchBoxDbId>27576</LaunchBoxDbId>
    <GameTitle>Tom Clancy's Ghost Recon: Predator</GameTitle>
    <GameFileName>Tom Clancy's Ghost Recon - Predator (Europe) (En,Fr,De,Es,It) (PSP) (PSN).iso</GameFileName>
    <GamePlatform>Sony PSP</GamePlatform>
    <ManualOrder>8</ManualOrder>
  </PlaylistGame>
  <PlaylistGame>
    <GameId>b5a6ea7b-d806-438f-98db-2b83569db0d9</GameId>
    <LaunchBoxDbId>9960</LaunchBoxDbId>
    <GameTitle>Tom Clancy's Ghost Recon: Future Soldier</GameTitle>
    <GameFileName>Future Soldier DX9.exe</GameFileName>
    <GamePlatform>Windows</GamePlatform>
    <ManualOrder>9</ManualOrder>
  </PlaylistGame>
  <PlaylistGame>
    <GameId>76a6652e-471d-4081-a4f3-f14081b573c8</GameId>
    <LaunchBoxDbId>35041</LaunchBoxDbId>
    <GameTitle>Tom Clancy's Ghost Recon: Wildlands</GameTitle>
    <GameFileName>rungame.exe</GameFileName>
    <GamePlatform>Sony Playstation 4</GamePlatform>
    <ManualOrder>10</ManualOrder>
  </PlaylistGame>
</LaunchBox>